BDXConverter/__init__.py
BDXConverter/Converter/Converter.py
BDXConverter/Converter/ErrorClassDefine.py
BDXConverter/Converter/FileOperation.py
BDXConverter/Converter/Signature.py
BDXConverter/Converter/__init__.py
BDXConverter/General/GeneralClass.py
BDXConverter/General/Operation.py
BDXConverter/General/Pool.py
BDXConverter/General/__init__.py
BDXConverter/Operation/AddInt16XValue.py
BDXConverter/Operation/AddInt16YValue.py
BDXConverter/Operation/AddInt16ZValue.py
BDXConverter/Operation/AddInt16ZValue0.py
BDXConverter/Operation/AddInt32XValue.py
BDXConverter/Operation/AddInt32YValue.py
BDXConverter/Operation/AddInt32ZValue.py
BDXConverter/Operation/AddInt32ZValue0.py
BDXConverter/Operation/AddInt8XValue.py
BDXConverter/Operation/AddInt8YValue.py
BDXConverter/Operation/AddInt8ZValue.py
BDXConverter/Operation/AddXValue.py
BDXConverter/Operation/AddYValue.py
BDXConverter/Operation/AddZValue.py
BDXConverter/Operation/AddZValue0.py
BDXConverter/Operation/AssignDebugData.py
BDXConverter/Operation/CreateConstantString.py
BDXConverter/Operation/NOP.py
BDXConverter/Operation/PlaceBlock.py
BDXConverter/Operation/PlaceBlockWithBlockStates.py
BDXConverter/Operation/PlaceBlockWithBlockStatesDeprecated.py
BDXConverter/Operation/PlaceBlockWithChestData.py
BDXConverter/Operation/PlaceBlockWithCommandBlockData.py
BDXConverter/Operation/PlaceBlockWithNBTData.py
BDXConverter/Operation/PlaceBlockWithRuntimeId.py
BDXConverter/Operation/PlaceCommandBlockWithCommandBlockData.py
BDXConverter/Operation/PlaceRuntimeBlock.py
BDXConverter/Operation/PlaceRuntimeBlockWithChestData.py
BDXConverter/Operation/PlaceRuntimeBlockWithChestDataAndUint32RuntimeID.py
BDXConverter/Operation/PlaceRuntimeBlockWithCommandBlockData.py
BDXConverter/Operation/PlaceRuntimeBlockWithCommandBlockDataAndUint32RuntimeID.py
BDXConverter/Operation/SetCommandBlockData.py
BDXConverter/Operation/SubtractXValue.py
BDXConverter/Operation/SubtractYValue.py
BDXConverter/Operation/SubtractZValue.py
BDXConverter-1.2.0.dist-info/LICENSE
BDXConverter-1.2.0.dist-info/METADATA
BDXConverter-1.2.0.dist-info/WHEEL
BDXConverter-1.2.0.dist-info/top_level.txt
BDXConverter-1.2.0.dist-info/RECORD
