Metadata-Version: 2.2
Name: BDXConverter
Version: 1.2.0
Summary: A code library to marshal, unmarshal, visual and reverse visualization of BDX files
Home-page: https://github.com/TriM-Organization/BDXConverter
Author: Minecraft Muti-Media Organization
Author-email: TriM-Organization@hotmail.com
Classifier: Programming Language :: Python :: 3
Classifier: License :: OSI Approved :: MIT License
Classifier: Operating System :: OS Independent
Requires-Python: >=3.9
License-File: LICENSE
Requires-Dist: brotli>=1.0.9
Requires-Dist: nbtlib>=2.0.4
Requires-Dist: pycryptodome>=3.17
Dynamic: author
Dynamic: author-email
Dynamic: classifier
Dynamic: description
Dynamic: description-content-type
Dynamic: home-page
Dynamic: requires-dist
Dynamic: requires-python
Dynamic: summary
